bentoml_core-0.1.0.dist-info/METADATA
bentoml_core-0.1.0.dist-info/WHEEL
bentoml_core-0.1.0.dist-info/license_files/LICENSE
bentoml_core/__init__.py
bentoml_core/__init__.pyi
bentoml_core/py.typed
bentoml_core/bentoml_core.cpython-37m-x86_64-linux-gnu.so
bentoml_core-0.1.0.dist-info/RECORD
