Metadata-Version: 2.1
Name: bentoml-core
Version: 0.1.0
Classifier: License :: OSI Approved :: Apache Software License
Classifier: Operating System :: OS Independent
Classifier: Programming Language :: Rust
Classifier: Programming Language :: Python :: 3
Classifier: Programming Language :: Python :: 3 :: Only
Classifier: Programming Language :: Python :: 3.7
Classifier: Programming Language :: Python :: 3.8
Classifier: Programming Language :: Python :: 3.9
Classifier: Programming Language :: Python :: 3.10
Classifier: Programming Language :: Python :: 3.11
Classifier: Programming Language :: Python :: Implementation :: CPython
Classifier: Topic :: Scientific/Engineering :: Artificial Intelligence
Classifier: Topic :: Software Development :: Libraries
License-File: LICENSE
Summary: The rust core of BentoML: The Unified Model Serving Framework
Keywords: MLOps,AI,BentoML,Model Serving,Model Deployment
Author-email: BentoML Team <contact@bentoml.com>
License: Apache-2.0
Requires-Python: >=3.7
Project-URL: Documentation, https://docs.bentoml.org/en/latest/
Project-URL: Bug Reports, https://github.com/bentoml/BentoML/issues
Project-URL: BentoML Community Slack, https://bit.ly/2N5IpbB
Project-URL: BentoML Official Blog, https://modelserving.com
Project-URL: BentoML Twitter, https://twitter.com/bentomlai
